{
  "patch": "CN Live",
  "lastUpdated": "2026-02-13 14:28",
  "source": "Tencent hero_list.js (WR list + icons) + hero_rank_list_v2 (CN stats)",
  "champions": [
    {
      "hero_id": "10119",
      "name": "Brand",
      "icon": "https://game.gtimg.cn/images/lgamem/act/lrlib/img/HeadIcon/H_S_10119.png",
      "stats": {
        "CN": {
          "win": 53.15,
          "pick": 10.01,
          "ban": 7.66
        }
      }
    },
    {
      "hero_id": "10138",
      "name": "Smolder",
      "icon": "https://game.gtimg.cn/images/lgamem/act/lrlib/img/HeadIcon/H_S_10138.png",
      "stats": {
        "CN": {
          "win": 56.35,
          "pick": 16.7,
          "ban": 74.47
        }
      }
    },
    {
      "hero_id": "10144",
      "name": "Viktor",
      "icon": "https://game.gtimg.cn/images/lgamem/act/lrlib/img/HeadIcon/H_S_10144.png",
      "stats": {
        "CN": {
          "win": 52.73,
          "pick": 6.4,
          "ban": 1.84
        }
      }
    },
    {
      "hero_id": "10028",
      "name": "Morgana",
      "icon": "https://game.gtimg.cn/images/lgamem/act/lrlib/img/HeadIcon/H_S_10028.png",
      "stats": {
        "CN": {
          "win": 52.7,
          "pick": 8.69,
          "ban": 32.41
        }
      }
    },
    {
      "hero_id": "10024",
      "name": "Syndra",
      "icon": "https://game.gtimg.cn/images/lgamem/act/lrlib/img/HeadIcon/H_S_10024.png",
      "stats": {
        "CN": {
          "win": 52.26,
          "pick": 9.0,
          "ban": 8.61
        }
      }
    },
    {
      "hero_id": "10122",
      "name": "Veigar",
      "icon": "https://game.gtimg.cn/images/lgamem/act/lrlib/img/HeadIcon/H_S_10122.png",
      "stats": {
        "CN": {
          "win": 53.21,
          "pick": 11.23,
          "ban": 16.01
        }
      }
    },
    {
      "hero_id": "10063",
      "name": "Zyra",
      "icon": "https://game.gtimg.cn/images/lgamem/act/lrlib/img/HeadIcon/H_S_10063.png",
      "stats": {
        "CN": {
          "win": 53.03,
          "pick": 4.86,
          "ban": 33.92
        }
      }
    },
    {
      "hero_id": "10046",
      "name": "Teemo",
      "icon": "https://game.gtimg.cn/images/lgamem/act/lrlib/img/HeadIcon/H_S_10046.png",
      "stats": {
        "CN": {
          "win": 55.27,
          "pick": 6.46,
          "ban": 25.57
        }
      }
    },
    {
      "hero_id": "10061",
      "name": "Kennen",
      "icon": "https://game.gtimg.cn/images/lgamem/act/lrlib/img/HeadIcon/H_S_10061.png",
      "stats": {
        "CN": {
          "win": 57.14,
          "pick": 4.31,
          "ban": 0.5
        }
      }
    },
    {
      "hero_id": "10109",
      "name": "Lissandra",
      "icon": "https://game.gtimg.cn/images/lgamem/act/lrlib/img/HeadIcon/H_S_10109.png",
      "stats": {
        "CN": {
          "win": 52.3,
          "pick": 8.16,
          "ban": 13.28
        }
      }
    },
    {
      "hero_id": "10003",
      "name": "Lux",
      "icon": "https://game.gtimg.cn/images/lgamem/act/lrlib/img/HeadIcon/H_S_10003.png",
      "stats": {
        "CN": {
          "win": 52.36,
          "pick": 12.52,
          "ban": 21.99
        }
      }
    },
    {
      "hero_id": "10090",
      "name": "Vladimir",
      "icon": "https://game.gtimg.cn/images/lgamem/act/lrlib/img/HeadIcon/H_S_10090.png",
      "stats": {
        "CN": {
          "win": 50.7,
          "pick": 5.53,
          "ban": 1.77
        }
      }
    },
    {
      "hero_id": "10012",
      "name": "Orianna",
      "icon": "https://game.gtimg.cn/images/lgamem/act/lrlib/img/HeadIcon/H_S_10012.png",
      "stats": {
        "CN": {
          "win": 52.42,
          "pick": 6.91,
          "ban": 0.39
        }
      }
    },
    {
      "hero_id": "10037",
      "name": "Yasuo",
      "icon": "https://game.gtimg.cn/images/lgamem/act/lrlib/img/HeadIcon/H_S_10037.png",
      "stats": {
        "CN": {
          "win": 52.34,
          "pick": 19.45,
          "ban": 32.54
        }
      }
    },
    {
      "hero_id": "10099",
      "name": "Galio",
      "icon": "https://game.gtimg.cn/images/lgamem/act/lrlib/img/HeadIcon/H_S_10099.png",
      "stats": {
        "CN": {
          "win": 50.99,
          "pick": 8.96,
          "ban": 2.17
        }
      }
    },
    {
      "hero_id": "10141",
      "name": "Vex",
      "icon": "https://game.gtimg.cn/images/lgamem/act/lrlib/img/HeadIcon/H_S_10141.png",
      "stats": {
        "CN": {
          "win": 52.74,
          "pick": 3.4,
          "ban": 0.82
        }
      }
    },
    {
      "hero_id": "10023",
      "name": "Aurelion Sol",
      "icon": "https://game.gtimg.cn/images/lgamem/act/lrlib/img/HeadIcon/H_S_10023.png",
      "stats": {
        "CN": {
          "win": 50.55,
          "pick": 10.85,
          "ban": 13.87
        }
      }
    },
    {
      "hero_id": "10038",
      "name": "Ahri",
      "icon": "https://game.gtimg.cn/images/lgamem/act/lrlib/img/HeadIcon/H_S_10038.png",
      "stats": {
        "CN": {
          "win": 52.36,
          "pick": 7.93,
          "ban": 0.41
        }
      }
    },
    {
      "hero_id": "10137",
      "name": "Ryze",
      "icon": "https://game.gtimg.cn/images/lgamem/act/lrlib/img/HeadIcon/H_S_10137.png",
      "stats": {
        "CN": {
          "win": 54.19,
          "pick": 9.42,
          "ban": 5.81
        }
      }
    },
    {
      "hero_id": "10087",
      "name": "Ziggs",
      "icon": "https://game.gtimg.cn/images/lgamem/act/lrlib/img/HeadIcon/H_S_10087.png",
      "stats": {
        "CN": {
          "win": 50.02,
          "pick": 6.73,
          "ban": 2.97
        }
      }
    },
    {
      "hero_id": "10127",
      "name": "Heimerdinger",
      "icon": "https://game.gtimg.cn/images/lgamem/act/lrlib/img/HeadIcon/H_S_10127.png",
      "stats": {
        "CN": {
          "win": 51.66,
          "pick": 2.08,
          "ban": 1.62
        }
      }
    },
    {
      "hero_id": "10069",
      "name": "Yone",
      "icon": "https://game.gtimg.cn/images/lgamem/act/lrlib/img/HeadIcon/H_S_10069.png",
      "stats": {
        "CN": {
          "win": 51.04,
          "pick": 9.32,
          "ban": 11.93
        }
      }
    },
    {
      "hero_id": "10086",
      "name": "Fizz",
      "icon": "https://game.gtimg.cn/images/lgamem/act/lrlib/img/HeadIcon/H_S_10086.png",
      "stats": {
        "CN": {
          "win": 52.35,
          "pick": 4.79,
          "ban": 6.31
        }
      }
    },
    {
      "hero_id": "10041",
      "name": "Kayle",
      "icon": "https://game.gtimg.cn/images/lgamem/act/lrlib/img/HeadIcon/H_S_10041.png",
      "stats": {
        "CN": {
          "win": 55.38,
          "pick": 4.0,
          "ban": 0.85
        }
      }
    },
    {
      "hero_id": "10025",
      "name": "Twisted Fate",
      "icon": "https://game.gtimg.cn/images/lgamem/act/lrlib/img/HeadIcon/H_S_10025.png",
      "stats": {
        "CN": {
          "win": 52.53,
          "pick": 9.45,
          "ban": 0.42
        }
      }
    },
    {
      "hero_id": "10126",
      "name": "Swain",
      "icon": "https://game.gtimg.cn/images/lgamem/act/lrlib/img/HeadIcon/H_S_10126.png",
      "stats": {
        "CN": {
          "win": 50.9,
          "pick": 7.9,
          "ban": 6.31
        }
      }
    },
    {
      "hero_id": "10039",
      "name": "Zed",
      "icon": "https://game.gtimg.cn/images/lgamem/act/lrlib/img/HeadIcon/H_S_10039.png",
      "stats": {
        "CN": {
          "win": 53.05,
          "pick": 6.27,
          "ban": 4.07
        }
      }
    },
    {
      "hero_id": "10085",
      "name": "Aurora",
      "icon": "https://game.gtimg.cn/images/lgamem/act/lrlib/img/HeadIcon/H_S_10085.png",
      "stats": {
        "CN": {
          "win": 51.43,
          "pick": 7.03,
          "ban": 16.22
        }
      }
    },
    {
      "hero_id": "10103",
      "name": "Kassadin",
      "icon": "https://game.gtimg.cn/images/lgamem/act/lrlib/img/HeadIcon/H_S_10103.png",
      "stats": {
        "CN": {
          "win": 51.72,
          "pick": 3.65,
          "ban": 0.98
        }
      }
    },
    {
      "hero_id": "10011",
      "name": "Ekko",
      "icon": "https://game.gtimg.cn/images/lgamem/act/lrlib/img/HeadIcon/H_S_10011.png",
      "stats": {
        "CN": {
          "win": 51.61,
          "pick": 2.31,
          "ban": 0.21
        }
      }
    },
    {
      "hero_id": "10013",
      "name": "Diana",
      "icon": "https://game.gtimg.cn/images/lgamem/act/lrlib/img/HeadIcon/H_S_10013.png",
      "stats": {
        "CN": {
          "win": 52.68,
          "pick": 1.6,
          "ban": 0.18
        }
      }
    },
    {
      "hero_id": "10034",
      "name": "Seraphine",
      "icon": "https://game.gtimg.cn/images/lgamem/act/lrlib/img/HeadIcon/H_S_10034.png",
      "stats": {
        "CN": {
          "win": 50.82,
          "pick": 10.89,
          "ban": 1.47
        }
      }
    },
    {
      "hero_id": "10094",
      "name": "Irelia",
      "icon": "https://game.gtimg.cn/images/lgamem/act/lrlib/img/HeadIcon/H_S_10094.png",
      "stats": {
        "CN": {
          "win": 52.79,
          "pick": 4.16,
          "ban": 4.38
        }
      }
    },
    {
      "hero_id": "10031",
      "name": "Akali",
      "icon": "https://game.gtimg.cn/images/lgamem/act/lrlib/img/HeadIcon/H_S_10031.png",
      "stats": {
        "CN": {
          "win": 51.98,
          "pick": 4.3,
          "ban": 1.17
        }
      }
    },
    {
      "hero_id": "10101",
      "name": "Jayce",
      "icon": "https://game.gtimg.cn/images/lgamem/act/lrlib/img/HeadIcon/H_S_10101.png",
      "stats": {
        "CN": {
          "win": 51.19,
          "pick": 4.01,
          "ban": 1.36
        }
      }
    },
    {
      "hero_id": "10036",
      "name": "Annie",
      "icon": "https://game.gtimg.cn/images/lgamem/act/lrlib/img/HeadIcon/H_S_10036.png",
      "stats": {
        "CN": {
          "win": 54.12,
          "pick": 2.16,
          "ban": 0.1
        }
      }
    },
    {
      "hero_id": "10095",
      "name": "Katarina",
      "icon": "https://game.gtimg.cn/images/lgamem/act/lrlib/img/HeadIcon/H_S_10095.png",
      "stats": {
        "CN": {
          "win": 51.85,
          "pick": 2.95,
          "ban": 0.68
        }
      }
    },
    {
      "hero_id": "10014",
      "name": "Zoe",
      "icon": "https://game.gtimg.cn/images/lgamem/act/lrlib/img/HeadIcon/H_S_10014.png",
      "stats": {
        "CN": {
          "win": 54.03,
          "pick": 1.71,
          "ban": 1.7
        }
      }
    },
    {
      "hero_id": "10134",
      "name": "Kalista",
      "icon": "https://game.gtimg.cn/images/lgamem/act/lrlib/img/HeadIcon/H_S_10134.png",
      "stats": {
        "CN": {
          "win": 53.58,
          "pick": 5.9,
          "ban": 3.82
        }
      }
    },
    {
      "hero_id": "10010",
      "name": "Vayne",
      "icon": "https://game.gtimg.cn/images/lgamem/act/lrlib/img/HeadIcon/H_S_10010.png",
      "stats": {
        "CN": {
          "win": 53.41,
          "pick": 15.35,
          "ban": 29.27
        }
      }
    },
    {
      "hero_id": "10125",
      "name": "Sion",
      "icon": "https://game.gtimg.cn/images/lgamem/act/lrlib/img/HeadIcon/H_S_10125.png",
      "stats": {
        "CN": {
          "win": 52.26,
          "pick": 5.35,
          "ban": 0.42
        }
      }
    },
    {
      "hero_id": "10068",
      "name": "Sett",
      "icon": "https://game.gtimg.cn/images/lgamem/act/lrlib/img/HeadIcon/H_S_10068.png",
      "stats": {
        "CN": {
          "win": 52.32,
          "pick": 12.98,
          "ban": 1.17
        }
      }
    },
    {
      "hero_id": "10082",
      "name": "Ambessa",
      "icon": "https://game.gtimg.cn/images/lgamem/act/lrlib/img/HeadIcon/H_S_10082.png",
      "stats": {
        "CN": {
          "win": 52.05,
          "pick": 4.05,
          "ban": 2.64
        }
      }
    },
    {
      "hero_id": "10118",
      "name": "Shen",
      "icon": "https://game.gtimg.cn/images/lgamem/act/lrlib/img/HeadIcon/H_S_10118.png",
      "stats": {
        "CN": {
          "win": 51.62,
          "pick": 1.6,
          "ban": 0.1
        }
      }
    },
    {
      "hero_id": "10136",
      "name": "Ornn",
      "icon": "https://game.gtimg.cn/images/lgamem/act/lrlib/img/HeadIcon/H_S_10136.png",
      "stats": {
        "CN": {
          "win": 54.58,
          "pick": 3.22,
          "ban": 0.27
        }
      }
    },
    {
      "hero_id": "10121",
      "name": "Renekton",
      "icon": "https://game.gtimg.cn/images/lgamem/act/lrlib/img/HeadIcon/H_S_10121.png",
      "stats": {
        "CN": {
          "win": 52.16,
          "pick": 12.78,
          "ban": 3.07
        }
      }
    },
    {
      "hero_id": "10102",
      "name": "Urgot",
      "icon": "https://game.gtimg.cn/images/lgamem/act/lrlib/img/HeadIcon/H_S_10102.png",
      "stats": {
        "CN": {
          "win": 51.67,
          "pick": 5.99,
          "ban": 3.44
        }
      }
    },
    {
      "hero_id": "10055",
      "name": "Camille",
      "icon": "https://game.gtimg.cn/images/lgamem/act/lrlib/img/HeadIcon/H_S_10055.png",
      "stats": {
        "CN": {
          "win": 50.73,
          "pick": 4.83,
          "ban": 0.53
        }
      }
    },
    {
      "hero_id": "10035",
      "name": "Mordekaiser",
      "icon": "https://game.gtimg.cn/images/lgamem/act/lrlib/img/HeadIcon/H_S_10035.png",
      "stats": {
        "CN": {
          "win": 50.62,
          "pick": 12.49,
          "ban": 32.34
        }
      }
    },
    {
      "hero_id": "10015",
      "name": "Tryndamere",
      "icon": "https://game.gtimg.cn/images/lgamem/act/lrlib/img/HeadIcon/H_S_10015.png",
      "stats": {
        "CN": {
          "win": 50.67,
          "pick": 9.1,
          "ban": 35.56
        }
      }
    },
    {
      "hero_id": "10140",
      "name": "Rumble",
      "icon": "https://game.gtimg.cn/images/lgamem/act/lrlib/img/HeadIcon/H_S_10140.png",
      "stats": {
        "CN": {
          "win": 52.16,
          "pick": 4.37,
          "ban": 1.84
        }
      }
    },
    {
      "hero_id": "10001",
      "name": "Garen",
      "icon": "https://game.gtimg.cn/images/lgamem/act/lrlib/img/HeadIcon/H_S_10001.png",
      "stats": {
        "CN": {
          "win": 51.05,
          "pick": 22.89,
          "ban": 5.97
        }
      }
    },
    {
      "hero_id": "10096",
      "name": "Singed",
      "icon": "https://game.gtimg.cn/images/lgamem/act/lrlib/img/HeadIcon/H_S_10096.png",
      "stats": {
        "CN": {
          "win": 56.0,
          "pick": 3.83,
          "ban": 0.63
        }
      }
    },
    {
      "hero_id": "10078",
      "name": "Gnar",
      "icon": "https://game.gtimg.cn/images/lgamem/act/lrlib/img/HeadIcon/H_S_10078.png",
      "stats": {
        "CN": {
          "win": 50.3,
          "pick": 2.51,
          "ban": 0.32
        }
      }
    },
    {
      "hero_id": "10058",
      "name": "Volibear",
      "icon": "https://game.gtimg.cn/images/lgamem/act/lrlib/img/HeadIcon/H_S_10058.png",
      "stats": {
        "CN": {
          "win": 49.69,
          "pick": 5.49,
          "ban": 5.54
        }
      }
    },
    {
      "hero_id": "10071",
      "name": "Darius",
      "icon": "https://game.gtimg.cn/images/lgamem/act/lrlib/img/HeadIcon/H_S_10071.png",
      "stats": {
        "CN": {
          "win": 50.4,
          "pick": 21.81,
          "ban": 8.92
        }
      }
    },
    {
      "hero_id": "10062",
      "name": "Dr. Mundo",
      "icon": "https://game.gtimg.cn/images/lgamem/act/lrlib/img/HeadIcon/H_S_10062.png",
      "stats": {
        "CN": {
          "win": 49.37,
          "pick": 5.17,
          "ban": 1.41
        }
      }
    },
    {
      "hero_id": "10065",
      "name": "Nasus",
      "icon": "https://game.gtimg.cn/images/lgamem/act/lrlib/img/HeadIcon/H_S_10065.png",
      "stats": {
        "CN": {
          "win": 51.92,
          "pick": 9.81,
          "ban": 14.39
        }
      }
    },
    {
      "hero_id": "10083",
      "name": "Malphite",
      "icon": "https://game.gtimg.cn/images/lgamem/act/lrlib/img/HeadIcon/H_S_10083.png",
      "stats": {
        "CN": {
          "win": 52.56,
          "pick": 11.01,
          "ban": 21.11
        }
      }
    },
    {
      "hero_id": "10076",
      "name": "Poppy",
      "icon": "https://game.gtimg.cn/images/lgamem/act/lrlib/img/HeadIcon/H_S_10076.png",
      "stats": {
        "CN": {
          "win": 54.55,
          "pick": 2.98,
          "ban": 0.61
        }
      }
    },
    {
      "hero_id": "10040",
      "name": "Jax",
      "icon": "https://game.gtimg.cn/images/lgamem/act/lrlib/img/HeadIcon/H_S_10040.png",
      "stats": {
        "CN": {
          "win": 49.62,
          "pick": 3.45,
          "ban": 0.47
        }
      }
    },
    {
      "hero_id": "10002",
      "name": "Aatrox",
      "icon": "https://game.gtimg.cn/images/lgamem/act/lrlib/img/HeadIcon/H_S_10002.png",
      "stats": {
        "CN": {
          "win": 50.06,
          "pick": 8.66,
          "ban": 10.93
        }
      }
    },
    {
      "hero_id": "10054",
      "name": "Gwen",
      "icon": "https://game.gtimg.cn/images/lgamem/act/lrlib/img/HeadIcon/H_S_10054.png",
      "stats": {
        "CN": {
          "win": 57.59,
          "pick": 2.96,
          "ban": 0.75
        }
      }
    },
    {
      "hero_id": "10032",
      "name": "Fiora",
      "icon": "https://game.gtimg.cn/images/lgamem/act/lrlib/img/HeadIcon/H_S_10032.png",
      "stats": {
        "CN": {
          "win": 51.1,
          "pick": 7.23,
          "ban": 10.65
        }
      }
    },
    {
      "hero_id": "10092",
      "name": "Riven",
      "icon": "https://game.gtimg.cn/images/lgamem/act/lrlib/img/HeadIcon/H_S_10092.png",
      "stats": {
        "CN": {
          "win": 56.72,
          "pick": 5.96,
          "ban": 4.86
        }
      }
    },
    {
      "hero_id": "10112",
      "name": "Caitlyn",
      "icon": "https://game.gtimg.cn/images/lgamem/act/lrlib/img/HeadIcon/H_S_10112.png",
      "stats": {
        "CN": {
          "win": 52.03,
          "pick": 27.88,
          "ban": 4.6
        }
      }
    },
    {
      "hero_id": "10079",
      "name": "Ashe",
      "icon": "https://game.gtimg.cn/images/lgamem/act/lrlib/img/HeadIcon/H_S_10079.png",
      "stats": {
        "CN": {
          "win": 51.5,
          "pick": 13.6,
          "ban": 0.33
        }
      }
    },
    {
      "hero_id": "10066",
      "name": "Miss Fortune",
      "icon": "https://game.gtimg.cn/images/lgamem/act/lrlib/img/HeadIcon/H_S_10066.png",
      "stats": {
        "CN": {
          "win": 51.45,
          "pick": 16.4,
          "ban": 2.38
        }
      }
    },
    {
      "hero_id": "10051",
      "name": "Xayah",
      "icon": "https://game.gtimg.cn/images/lgamem/act/lrlib/img/HeadIcon/H_S_10051.png",
      "stats": {
        "CN": {
          "win": 52.78,
          "pick": 8.23,
          "ban": 0.38
        }
      }
    },
    {
      "hero_id": "10018",
      "name": "Jinx",
      "icon": "https://game.gtimg.cn/images/lgamem/act/lrlib/img/HeadIcon/H_S_10018.png",
      "stats": {
        "CN": {
          "win": 50.68,
          "pick": 16.87,
          "ban": 1.0
        }
      }
    },
    {
      "hero_id": "10022",
      "name": "Jhin",
      "icon": "https://game.gtimg.cn/images/lgamem/act/lrlib/img/HeadIcon/H_S_10022.png",
      "stats": {
        "CN": {
          "win": 50.47,
          "pick": 15.03,
          "ban": 0.37
        }
      }
    },
    {
      "hero_id": "10104",
      "name": "Samira",
      "icon": "https://game.gtimg.cn/images/lgamem/act/lrlib/img/HeadIcon/H_S_10104.png",
      "stats": {
        "CN": {
          "win": 50.64,
          "pick": 13.17,
          "ban": 8.63
        }
      }
    },
    {
      "hero_id": "10045",
      "name": "Tristana",
      "icon": "https://game.gtimg.cn/images/lgamem/act/lrlib/img/HeadIcon/H_S_10045.png",
      "stats": {
        "CN": {
          "win": 49.52,
          "pick": 6.9,
          "ban": 0.2
        }
      }
    },
    {
      "hero_id": "10093",
      "name": "Varus",
      "icon": "https://game.gtimg.cn/images/lgamem/act/lrlib/img/HeadIcon/H_S_10093.png",
      "stats": {
        "CN": {
          "win": 48.87,
          "pick": 6.42,
          "ban": 0.83
        }
      }
    },
    {
      "hero_id": "10107",
      "name": "Sivir",
      "icon": "https://game.gtimg.cn/images/lgamem/act/lrlib/img/HeadIcon/H_S_10107.png",
      "stats": {
        "CN": {
          "win": 48.78,
          "pick": 3.76,
          "ban": 0.08
        }
      }
    },
    {
      "hero_id": "10053",
      "name": "Twitch",
      "icon": "https://game.gtimg.cn/images/lgamem/act/lrlib/img/HeadIcon/H_S_10053.png",
      "stats": {
        "CN": {
          "win": 48.76,
          "pick": 5.1,
          "ban": 0.31
        }
      }
    },
    {
      "hero_id": "10042",
      "name": "Lucian",
      "icon": "https://game.gtimg.cn/images/lgamem/act/lrlib/img/HeadIcon/H_S_10042.png",
      "stats": {
        "CN": {
          "win": 50.08,
          "pick": 16.12,
          "ban": 2.97
        }
      }
    },
    {
      "hero_id": "10098",
      "name": "Ezreal",
      "icon": "https://game.gtimg.cn/images/lgamem/act/lrlib/img/HeadIcon/H_S_10098.png",
      "stats": {
        "CN": {
          "win": 52.34,
          "pick": 13.55,
          "ban": 0.48
        }
      }
    },
    {
      "hero_id": "10026",
      "name": "Kai'Sa",
      "icon": "https://game.gtimg.cn/images/lgamem/act/lrlib/img/HeadIcon/H_S_10026.png",
      "stats": {
        "CN": {
          "win": 48.65,
          "pick": 21.4,
          "ban": 0.95
        }
      }
    },
    {
      "hero_id": "10077",
      "name": "Draven",
      "icon": "https://game.gtimg.cn/images/lgamem/act/lrlib/img/HeadIcon/H_S_10077.png",
      "stats": {
        "CN": {
          "win": 50.62,
          "pick": 10.5,
          "ban": 7.82
        }
      }
    },
    {
      "hero_id": "10067",
      "name": "Zeri",
      "icon": "https://game.gtimg.cn/images/lgamem/act/lrlib/img/HeadIcon/H_S_10067.png",
      "stats": {
        "CN": {
          "win": 48.09,
          "pick": 2.65,
          "ban": 0.04
        }
      }
    },
    {
      "hero_id": "10021",
      "name": "Braum",
      "icon": "https://game.gtimg.cn/images/lgamem/act/lrlib/img/HeadIcon/H_S_10021.png",
      "stats": {
        "CN": {
          "win": 54.72,
          "pick": 6.41,
          "ban": 1.54
        }
      }
    },
    {
      "hero_id": "10075",
      "name": "Janna",
      "icon": "https://game.gtimg.cn/images/lgamem/act/lrlib/img/HeadIcon/H_S_10075.png",
      "stats": {
        "CN": {
          "win": 57.07,
          "pick": 5.15,
          "ban": 0.46
        }
      }
    },
    {
      "hero_id": "10123",
      "name": "Senna",
      "icon": "https://game.gtimg.cn/images/lgamem/act/lrlib/img/HeadIcon/H_S_10123.png",
      "stats": {
        "CN": {
          "win": 52.67,
          "pick": 4.89,
          "ban": 0.76
        }
      }
    },
    {
      "hero_id": "10074",
      "name": "Maokai",
      "icon": "https://game.gtimg.cn/images/lgamem/act/lrlib/img/HeadIcon/H_S_10074.png",
      "stats": {
        "CN": {
          "win": 52.5,
          "pick": 4.88,
          "ban": 0.47
        }
      }
    },
    {
      "hero_id": "10007",
      "name": "Karma",
      "icon": "https://game.gtimg.cn/images/lgamem/act/lrlib/img/HeadIcon/H_S_10007.png",
      "stats": {
        "CN": {
          "win": 52.35,
          "pick": 14.0,
          "ban": 0.71
        }
      }
    },
    {
      "hero_id": "10091",
      "name": "Nami",
      "icon": "https://game.gtimg.cn/images/lgamem/act/lrlib/img/HeadIcon/H_S_10091.png",
      "stats": {
        "CN": {
          "win": 52.3,
          "pick": 12.14,
          "ban": 0.47
        }
      }
    },
    {
      "hero_id": "10132",
      "name": "Nautilus",
      "icon": "https://game.gtimg.cn/images/lgamem/act/lrlib/img/HeadIcon/H_S_10132.png",
      "stats": {
        "CN": {
          "win": 52.62,
          "pick": 13.84,
          "ban": 4.87
        }
      }
    },
    {
      "hero_id": "10108",
      "name": "Milio",
      "icon": "https://game.gtimg.cn/images/lgamem/act/lrlib/img/HeadIcon/H_S_10108.png",
      "stats": {
        "CN": {
          "win": 51.37,
          "pick": 11.74,
          "ban": 18.65
        }
      }
    },
    {
      "hero_id": "10097",
      "name": "Soraka",
      "icon": "https://game.gtimg.cn/images/lgamem/act/lrlib/img/HeadIcon/H_S_10097.png",
      "stats": {
        "CN": {
          "win": 51.1,
          "pick": 5.11,
          "ban": 1.51
        }
      }
    },
    {
      "hero_id": "10080",
      "name": "Zilean",
      "icon": "https://game.gtimg.cn/images/lgamem/act/lrlib/img/HeadIcon/H_S_10080.png",
      "stats": {
        "CN": {
          "win": 53.59,
          "pick": 3.5,
          "ban": 9.86
        }
      }
    },
    {
      "hero_id": "10044",
      "name": "Leona",
      "icon": "https://game.gtimg.cn/images/lgamem/act/lrlib/img/HeadIcon/H_S_10044.png",
      "stats": {
        "CN": {
          "win": 51.37,
          "pick": 11.59,
          "ban": 7.11
        }
      }
    },
    {
      "hero_id": "10048",
      "name": "Lulu",
      "icon": "https://game.gtimg.cn/images/lgamem/act/lrlib/img/HeadIcon/H_S_10048.png",
      "stats": {
        "CN": {
          "win": 49.82,
          "pick": 18.49,
          "ban": 21.51
        }
      }
    },
    {
      "hero_id": "10052",
      "name": "Rakan",
      "icon": "https://game.gtimg.cn/images/lgamem/act/lrlib/img/HeadIcon/H_S_10052.png",
      "stats": {
        "CN": {
          "win": 54.08,
          "pick": 5.5,
          "ban": 0.61
        }
      }
    },
    {
      "hero_id": "10124",
      "name": "Pyke",
      "icon": "https://game.gtimg.cn/images/lgamem/act/lrlib/img/HeadIcon/H_S_10124.png",
      "stats": {
        "CN": {
          "win": 50.99,
          "pick": 5.83,
          "ban": 2.07
        }
      }
    },
    {
      "hero_id": "10033",
      "name": "Blitzcrank",
      "icon": "https://game.gtimg.cn/images/lgamem/act/lrlib/img/HeadIcon/H_S_10033.png",
      "stats": {
        "CN": {
          "win": 51.77,
          "pick": 9.8,
          "ban": 3.3
        }
      }
    },
    {
      "hero_id": "10081",
      "name": "Alistar",
      "icon": "https://game.gtimg.cn/images/lgamem/act/lrlib/img/HeadIcon/H_S_10081.png",
      "stats": {
        "CN": {
          "win": 51.03,
          "pick": 6.21,
          "ban": 0.67
        }
      }
    },
    {
      "hero_id": "10116",
      "name": "Rell",
      "icon": "https://game.gtimg.cn/images/lgamem/act/lrlib/img/HeadIcon/H_S_10116.png",
      "stats": {
        "CN": {
          "win": 49.84,
          "pick": 4.24,
          "ban": 2.94
        }
      }
    },
    {
      "hero_id": "10130",
      "name": "Thresh",
      "icon": "https://game.gtimg.cn/images/lgamem/act/lrlib/img/HeadIcon/H_S_10130.png",
      "stats": {
        "CN": {
          "win": 54.28,
          "pick": 12.65,
          "ban": 5.09
        }
      }
    },
    {
      "hero_id": "10047",
      "name": "Sona",
      "icon": "https://game.gtimg.cn/images/lgamem/act/lrlib/img/HeadIcon/H_S_10047.png",
      "stats": {
        "CN": {
          "win": 52.8,
          "pick": 4.62,
          "ban": 0.09
        }
      }
    },
    {
      "hero_id": "10105",
      "name": "Bard",
      "icon": "https://game.gtimg.cn/images/lgamem/act/lrlib/img/HeadIcon/H_S_10105.png",
      "stats": {
        "CN": {
          "win": 56.08,
          "pick": 4.19,
          "ban": 34.26
        }
      }
    },
    {
      "hero_id": "10020",
      "name": "Yuumi",
      "icon": "https://game.gtimg.cn/images/lgamem/act/lrlib/img/HeadIcon/H_S_10020.png",
      "stats": {
        "CN": {
          "win": 46.16,
          "pick": 15.07,
          "ban": 33.38
        }
      }
    },
    {
      "hero_id": "10064",
      "name": "Rammus",
      "icon": "https://game.gtimg.cn/images/lgamem/act/lrlib/img/HeadIcon/H_S_10064.png",
      "stats": {
        "CN": {
          "win": 55.09,
          "pick": 7.23,
          "ban": 13.62
        }
      }
    },
    {
      "hero_id": "10070",
      "name": "Master Yi",
      "icon": "https://game.gtimg.cn/images/lgamem/act/lrlib/img/HeadIcon/H_S_10070.png",
      "stats": {
        "CN": {
          "win": 54.8,
          "pick": 20.37,
          "ban": 86.21
        }
      }
    },
    {
      "hero_id": "10072",
      "name": "Graves",
      "icon": "https://game.gtimg.cn/images/lgamem/act/lrlib/img/HeadIcon/H_S_10072.png",
      "stats": {
        "CN": {
          "win": 53.71,
          "pick": 10.56,
          "ban": 1.13
        }
      }
    },
    {
      "hero_id": "10135",
      "name": "Lillia",
      "icon": "https://game.gtimg.cn/images/lgamem/act/lrlib/img/HeadIcon/H_S_10135.png",
      "stats": {
        "CN": {
          "win": 53.56,
          "pick": 5.95,
          "ban": 3.14
        }
      }
    },
    {
      "hero_id": "10004",
      "name": "Amumu",
      "icon": "https://game.gtimg.cn/images/lgamem/act/lrlib/img/HeadIcon/H_S_10004.png",
      "stats": {
        "CN": {
          "win": 56.01,
          "pick": 4.31,
          "ban": 0.19
        }
      }
    },
    {
      "hero_id": "10049",
      "name": "Shyvana",
      "icon": "https://game.gtimg.cn/images/lgamem/act/lrlib/img/HeadIcon/H_S_10049.png",
      "stats": {
        "CN": {
          "win": 52.81,
          "pick": 11.3,
          "ban": 18.27
        }
      }
    },
    {
      "hero_id": "10131",
      "name": "Warwick",
      "icon": "https://game.gtimg.cn/images/lgamem/act/lrlib/img/HeadIcon/H_S_10131.png",
      "stats": {
        "CN": {
          "win": 53.98,
          "pick": 4.99,
          "ban": 3.01
        }
      }
    },
    {
      "hero_id": "10057",
      "name": "Viego",
      "icon": "https://game.gtimg.cn/images/lgamem/act/lrlib/img/HeadIcon/H_S_10057.png",
      "stats": {
        "CN": {
          "win": 51.9,
          "pick": 12.87,
          "ban": 16.41
        }
      }
    },
    {
      "hero_id": "10008",
      "name": "Nunu & Willump",
      "icon": "https://game.gtimg.cn/images/lgamem/act/lrlib/img/HeadIcon/H_S_10008.png",
      "stats": {
        "CN": {
          "win": 53.42,
          "pick": 2.36,
          "ban": 1.98
        }
      }
    },
    {
      "hero_id": "10056",
      "name": "Jarvan IV",
      "icon": "https://game.gtimg.cn/images/lgamem/act/lrlib/img/HeadIcon/H_S_10056.png",
      "stats": {
        "CN": {
          "win": 51.57,
          "pick": 6.54,
          "ban": 0.6
        }
      }
    },
    {
      "hero_id": "10050",
      "name": "Vi",
      "icon": "https://game.gtimg.cn/images/lgamem/act/lrlib/img/HeadIcon/H_S_10050.png",
      "stats": {
        "CN": {
          "win": 52.39,
          "pick": 7.83,
          "ban": 1.12
        }
      }
    },
    {
      "hero_id": "10073",
      "name": "Kindred",
      "icon": "https://game.gtimg.cn/images/lgamem/act/lrlib/img/HeadIcon/H_S_10073.png",
      "stats": {
        "CN": {
          "win": 54.63,
          "pick": 2.67,
          "ban": 0.38
        }
      }
    },
    {
      "hero_id": "10005",
      "name": "Kayn",
      "icon": "https://game.gtimg.cn/images/lgamem/act/lrlib/img/HeadIcon/H_S_10005.png",
      "stats": {
        "CN": {
          "win": 50.29,
          "pick": 5.36,
          "ban": 0.3
        }
      }
    },
    {
      "hero_id": "10016",
      "name": "Xin Zhao",
      "icon": "https://game.gtimg.cn/images/lgamem/act/lrlib/img/HeadIcon/H_S_10016.png",
      "stats": {
        "CN": {
          "win": 52.39,
          "pick": 10.98,
          "ban": 3.09
        }
      }
    },
    {
      "hero_id": "10017",
      "name": "Kha'Zix",
      "icon": "https://game.gtimg.cn/images/lgamem/act/lrlib/img/HeadIcon/H_S_10017.png",
      "stats": {
        "CN": {
          "win": 49.78,
          "pick": 5.93,
          "ban": 0.46
        }
      }
    },
    {
      "hero_id": "10030",
      "name": "Pantheon",
      "icon": "https://game.gtimg.cn/images/lgamem/act/lrlib/img/HeadIcon/H_S_10030.png",
      "stats": {
        "CN": {
          "win": 51.86,
          "pick": 5.16,
          "ban": 3.21
        }
      }
    },
    {
      "hero_id": "10133",
      "name": "Fiddlesticks",
      "icon": "https://game.gtimg.cn/images/lgamem/act/lrlib/img/HeadIcon/H_S_10133.png",
      "stats": {
        "CN": {
          "win": 53.57,
          "pick": 3.32,
          "ban": 2.13
        }
      }
    },
    {
      "hero_id": "10029",
      "name": "Evelynn",
      "icon": "https://game.gtimg.cn/images/lgamem/act/lrlib/img/HeadIcon/H_S_10029.png",
      "stats": {
        "CN": {
          "win": 53.36,
          "pick": 4.64,
          "ban": 5.46
        }
      }
    },
    {
      "hero_id": "10151",
      "name": "Nocturne",
      "icon": "https://game.gtimg.cn/images/lgamem/act/lrlib/img/HeadIcon/H_S_10151.png",
      "stats": {
        "CN": {
          "win": 51.17,
          "pick": 4.16,
          "ban": 24.09
        }
      }
    },
    {
      "hero_id": "10128",
      "name": "Talon",
      "icon": "https://game.gtimg.cn/images/lgamem/act/lrlib/img/HeadIcon/H_S_10128.png",
      "stats": {
        "CN": {
          "win": 50.26,
          "pick": 6.07,
          "ban": 2.3
        }
      }
    },
    {
      "hero_id": "10106",
      "name": "Olaf",
      "icon": "https://game.gtimg.cn/images/lgamem/act/lrlib/img/HeadIcon/H_S_10106.png",
      "stats": {
        "CN": {
          "win": 52.1,
          "pick": 2.45,
          "ban": 2.46
        }
      }
    },
    {
      "hero_id": "10084",
      "name": "Nidalee",
      "icon": "https://game.gtimg.cn/images/lgamem/act/lrlib/img/HeadIcon/H_S_10084.png",
      "stats": {
        "CN": {
          "win": 57.51,
          "pick": 3.26,
          "ban": 27.53
        }
      }
    },
    {
      "hero_id": "10006",
      "name": "Rengar",
      "icon": "https://game.gtimg.cn/images/lgamem/act/lrlib/img/HeadIcon/H_S_10006.png",
      "stats": {
        "CN": {
          "win": 51.83,
          "pick": 2.27,
          "ban": 2.43
        }
      }
    },
    {
      "hero_id": "10019",
      "name": "Hecarim",
      "icon": "https://game.gtimg.cn/images/lgamem/act/lrlib/img/HeadIcon/H_S_10019.png",
      "stats": {
        "CN": {
          "win": 56.88,
          "pick": 7.85,
          "ban": 84.96
        }
      }
    },
    {
      "hero_id": "10060",
      "name": "Corki",
      "icon": "https://game.gtimg.cn/images/lgamem/act/lrlib/img/HeadIcon/H_S_10060.png",
      "stats": {
        "CN": {
          "win": 50.18,
          "pick": 2.17,
          "ban": 0.02
        }
      }
    },
    {
      "hero_id": "10089",
      "name": "Gragas",
      "icon": "https://game.gtimg.cn/images/lgamem/act/lrlib/img/HeadIcon/H_S_10089.png",
      "stats": {
        "CN": {
          "win": 57.72,
          "pick": 2.36,
          "ban": 0.1
        }
      }
    },
    {
      "hero_id": "10027",
      "name": "Nilah",
      "icon": "https://game.gtimg.cn/images/lgamem/act/lrlib/img/HeadIcon/H_S_10027.png",
      "stats": {
        "CN": {
          "win": 52.77,
          "pick": 1.48,
          "ban": 0.99
        }
      }
    },
    {
      "hero_id": "10100",
      "name": "Akshan",
      "icon": "https://game.gtimg.cn/images/lgamem/act/lrlib/img/HeadIcon/H_S_10100.png",
      "stats": {
        "CN": {
          "win": 57.76,
          "pick": 1.21,
          "ban": 0.05
        }
      }
    }
  ],
  "statsByName": {
    "Brand": {
      "win": 53.15,
      "pick": 10.01,
      "ban": 7.66
    },
    "Smolder": {
      "win": 56.35,
      "pick": 16.7,
      "ban": 74.47
    },
    "Viktor": {
      "win": 52.73,
      "pick": 6.4,
      "ban": 1.84
    },
    "Morgana": {
      "win": 52.7,
      "pick": 8.69,
      "ban": 32.41
    },
    "Syndra": {
      "win": 52.26,
      "pick": 9.0,
      "ban": 8.61
    },
    "Veigar": {
      "win": 53.21,
      "pick": 11.23,
      "ban": 16.01
    },
    "Zyra": {
      "win": 53.03,
      "pick": 4.86,
      "ban": 33.92
    },
    "Teemo": {
      "win": 55.27,
      "pick": 6.46,
      "ban": 25.57
    },
    "Kennen": {
      "win": 57.14,
      "pick": 4.31,
      "ban": 0.5
    },
    "Lissandra": {
      "win": 52.3,
      "pick": 8.16,
      "ban": 13.28
    },
    "Lux": {
      "win": 52.36,
      "pick": 12.52,
      "ban": 21.99
    },
    "Vladimir": {
      "win": 50.7,
      "pick": 5.53,
      "ban": 1.77
    },
    "Orianna": {
      "win": 52.42,
      "pick": 6.91,
      "ban": 0.39
    },
    "Yasuo": {
      "win": 52.34,
      "pick": 19.45,
      "ban": 32.54
    },
    "Galio": {
      "win": 50.99,
      "pick": 8.96,
      "ban": 2.17
    },
    "Vex": {
      "win": 52.74,
      "pick": 3.4,
      "ban": 0.82
    },
    "Aurelion Sol": {
      "win": 50.55,
      "pick": 10.85,
      "ban": 13.87
    },
    "Ahri": {
      "win": 52.36,
      "pick": 7.93,
      "ban": 0.41
    },
    "Ryze": {
      "win": 54.19,
      "pick": 9.42,
      "ban": 5.81
    },
    "Ziggs": {
      "win": 50.02,
      "pick": 6.73,
      "ban": 2.97
    },
    "Heimerdinger": {
      "win": 51.66,
      "pick": 2.08,
      "ban": 1.62
    },
    "Yone": {
      "win": 51.04,
      "pick": 9.32,
      "ban": 11.93
    },
    "Fizz": {
      "win": 52.35,
      "pick": 4.79,
      "ban": 6.31
    },
    "Kayle": {
      "win": 55.38,
      "pick": 4.0,
      "ban": 0.85
    },
    "Twisted Fate": {
      "win": 52.53,
      "pick": 9.45,
      "ban": 0.42
    },
    "Swain": {
      "win": 50.9,
      "pick": 7.9,
      "ban": 6.31
    },
    "Zed": {
      "win": 53.05,
      "pick": 6.27,
      "ban": 4.07
    },
    "Aurora": {
      "win": 51.43,
      "pick": 7.03,
      "ban": 16.22
    },
    "Kassadin": {
      "win": 51.72,
      "pick": 3.65,
      "ban": 0.98
    },
    "Ekko": {
      "win": 51.61,
      "pick": 2.31,
      "ban": 0.21
    },
    "Diana": {
      "win": 52.68,
      "pick": 1.6,
      "ban": 0.18
    },
    "Seraphine": {
      "win": 50.82,
      "pick": 10.89,
      "ban": 1.47
    },
    "Irelia": {
      "win": 52.79,
      "pick": 4.16,
      "ban": 4.38
    },
    "Akali": {
      "win": 51.98,
      "pick": 4.3,
      "ban": 1.17
    },
    "Jayce": {
      "win": 51.19,
      "pick": 4.01,
      "ban": 1.36
    },
    "Annie": {
      "win": 54.12,
      "pick": 2.16,
      "ban": 0.1
    },
    "Katarina": {
      "win": 51.85,
      "pick": 2.95,
      "ban": 0.68
    },
    "Zoe": {
      "win": 54.03,
      "pick": 1.71,
      "ban": 1.7
    },
    "Kalista": {
      "win": 53.58,
      "pick": 5.9,
      "ban": 3.82
    },
    "Vayne": {
      "win": 53.41,
      "pick": 15.35,
      "ban": 29.27
    },
    "Sion": {
      "win": 52.26,
      "pick": 5.35,
      "ban": 0.42
    },
    "Sett": {
      "win": 52.32,
      "pick": 12.98,
      "ban": 1.17
    },
    "Ambessa": {
      "win": 52.05,
      "pick": 4.05,
      "ban": 2.64
    },
    "Shen": {
      "win": 51.62,
      "pick": 1.6,
      "ban": 0.1
    },
    "Ornn": {
      "win": 54.58,
      "pick": 3.22,
      "ban": 0.27
    },
    "Renekton": {
      "win": 52.16,
      "pick": 12.78,
      "ban": 3.07
    },
    "Urgot": {
      "win": 51.67,
      "pick": 5.99,
      "ban": 3.44
    },
    "Camille": {
      "win": 50.73,
      "pick": 4.83,
      "ban": 0.53
    },
    "Mordekaiser": {
      "win": 50.62,
      "pick": 12.49,
      "ban": 32.34
    },
    "Tryndamere": {
      "win": 50.67,
      "pick": 9.1,
      "ban": 35.56
    },
    "Rumble": {
      "win": 52.16,
      "pick": 4.37,
      "ban": 1.84
    },
    "Garen": {
      "win": 51.05,
      "pick": 22.89,
      "ban": 5.97
    },
    "Singed": {
      "win": 56.0,
      "pick": 3.83,
      "ban": 0.63
    },
    "Gnar": {
      "win": 50.3,
      "pick": 2.51,
      "ban": 0.32
    },
    "Volibear": {
      "win": 49.69,
      "pick": 5.49,
      "ban": 5.54
    },
    "Darius": {
      "win": 50.4,
      "pick": 21.81,
      "ban": 8.92
    },
    "Dr. Mundo": {
      "win": 49.37,
      "pick": 5.17,
      "ban": 1.41
    },
    "Nasus": {
      "win": 51.92,
      "pick": 9.81,
      "ban": 14.39
    },
    "Malphite": {
      "win": 52.56,
      "pick": 11.01,
      "ban": 21.11
    },
    "Poppy": {
      "win": 54.55,
      "pick": 2.98,
      "ban": 0.61
    },
    "Jax": {
      "win": 49.62,
      "pick": 3.45,
      "ban": 0.47
    },
    "Aatrox": {
      "win": 50.06,
      "pick": 8.66,
      "ban": 10.93
    },
    "Gwen": {
      "win": 57.59,
      "pick": 2.96,
      "ban": 0.75
    },
    "Fiora": {
      "win": 51.1,
      "pick": 7.23,
      "ban": 10.65
    },
    "Riven": {
      "win": 56.72,
      "pick": 5.96,
      "ban": 4.86
    },
    "Caitlyn": {
      "win": 52.03,
      "pick": 27.88,
      "ban": 4.6
    },
    "Ashe": {
      "win": 51.5,
      "pick": 13.6,
      "ban": 0.33
    },
    "Miss Fortune": {
      "win": 51.45,
      "pick": 16.4,
      "ban": 2.38
    },
    "Xayah": {
      "win": 52.78,
      "pick": 8.23,
      "ban": 0.38
    },
    "Jinx": {
      "win": 50.68,
      "pick": 16.87,
      "ban": 1.0
    },
    "Jhin": {
      "win": 50.47,
      "pick": 15.03,
      "ban": 0.37
    },
    "Samira": {
      "win": 50.64,
      "pick": 13.17,
      "ban": 8.63
    },
    "Tristana": {
      "win": 49.52,
      "pick": 6.9,
      "ban": 0.2
    },
    "Varus": {
      "win": 48.87,
      "pick": 6.42,
      "ban": 0.83
    },
    "Sivir": {
      "win": 48.78,
      "pick": 3.76,
      "ban": 0.08
    },
    "Twitch": {
      "win": 48.76,
      "pick": 5.1,
      "ban": 0.31
    },
    "Lucian": {
      "win": 50.08,
      "pick": 16.12,
      "ban": 2.97
    },
    "Ezreal": {
      "win": 52.34,
      "pick": 13.55,
      "ban": 0.48
    },
    "Kai'Sa": {
      "win": 48.65,
      "pick": 21.4,
      "ban": 0.95
    },
    "Draven": {
      "win": 50.62,
      "pick": 10.5,
      "ban": 7.82
    },
    "Zeri": {
      "win": 48.09,
      "pick": 2.65,
      "ban": 0.04
    },
    "Braum": {
      "win": 54.72,
      "pick": 6.41,
      "ban": 1.54
    },
    "Janna": {
      "win": 57.07,
      "pick": 5.15,
      "ban": 0.46
    },
    "Senna": {
      "win": 52.67,
      "pick": 4.89,
      "ban": 0.76
    },
    "Maokai": {
      "win": 52.5,
      "pick": 4.88,
      "ban": 0.47
    },
    "Karma": {
      "win": 52.35,
      "pick": 14.0,
      "ban": 0.71
    },
    "Nami": {
      "win": 52.3,
      "pick": 12.14,
      "ban": 0.47
    },
    "Nautilus": {
      "win": 52.62,
      "pick": 13.84,
      "ban": 4.87
    },
    "Milio": {
      "win": 51.37,
      "pick": 11.74,
      "ban": 18.65
    },
    "Soraka": {
      "win": 51.1,
      "pick": 5.11,
      "ban": 1.51
    },
    "Zilean": {
      "win": 53.59,
      "pick": 3.5,
      "ban": 9.86
    },
    "Leona": {
      "win": 51.37,
      "pick": 11.59,
      "ban": 7.11
    },
    "Lulu": {
      "win": 49.82,
      "pick": 18.49,
      "ban": 21.51
    },
    "Rakan": {
      "win": 54.08,
      "pick": 5.5,
      "ban": 0.61
    },
    "Pyke": {
      "win": 50.99,
      "pick": 5.83,
      "ban": 2.07
    },
    "Blitzcrank": {
      "win": 51.77,
      "pick": 9.8,
      "ban": 3.3
    },
    "Alistar": {
      "win": 51.03,
      "pick": 6.21,
      "ban": 0.67
    },
    "Rell": {
      "win": 49.84,
      "pick": 4.24,
      "ban": 2.94
    },
    "Thresh": {
      "win": 54.28,
      "pick": 12.65,
      "ban": 5.09
    },
    "Sona": {
      "win": 52.8,
      "pick": 4.62,
      "ban": 0.09
    },
    "Bard": {
      "win": 56.08,
      "pick": 4.19,
      "ban": 34.26
    },
    "Yuumi": {
      "win": 46.16,
      "pick": 15.07,
      "ban": 33.38
    },
    "Rammus": {
      "win": 55.09,
      "pick": 7.23,
      "ban": 13.62
    },
    "Master Yi": {
      "win": 54.8,
      "pick": 20.37,
      "ban": 86.21
    },
    "Graves": {
      "win": 53.71,
      "pick": 10.56,
      "ban": 1.13
    },
    "Lillia": {
      "win": 53.56,
      "pick": 5.95,
      "ban": 3.14
    },
    "Amumu": {
      "win": 56.01,
      "pick": 4.31,
      "ban": 0.19
    },
    "Shyvana": {
      "win": 52.81,
      "pick": 11.3,
      "ban": 18.27
    },
    "Warwick": {
      "win": 53.98,
      "pick": 4.99,
      "ban": 3.01
    },
    "Viego": {
      "win": 51.9,
      "pick": 12.87,
      "ban": 16.41
    },
    "Nunu & Willump": {
      "win": 53.42,
      "pick": 2.36,
      "ban": 1.98
    },
    "Jarvan IV": {
      "win": 51.57,
      "pick": 6.54,
      "ban": 0.6
    },
    "Vi": {
      "win": 52.39,
      "pick": 7.83,
      "ban": 1.12
    },
    "Kindred": {
      "win": 54.63,
      "pick": 2.67,
      "ban": 0.38
    },
    "Kayn": {
      "win": 50.29,
      "pick": 5.36,
      "ban": 0.3
    },
    "Xin Zhao": {
      "win": 52.39,
      "pick": 10.98,
      "ban": 3.09
    },
    "Kha'Zix": {
      "win": 49.78,
      "pick": 5.93,
      "ban": 0.46
    },
    "Pantheon": {
      "win": 51.86,
      "pick": 5.16,
      "ban": 3.21
    },
    "Fiddlesticks": {
      "win": 53.57,
      "pick": 3.32,
      "ban": 2.13
    },
    "Evelynn": {
      "win": 53.36,
      "pick": 4.64,
      "ban": 5.46
    },
    "Nocturne": {
      "win": 51.17,
      "pick": 4.16,
      "ban": 24.09
    },
    "Talon": {
      "win": 50.26,
      "pick": 6.07,
      "ban": 2.3
    },
    "Olaf": {
      "win": 52.1,
      "pick": 2.45,
      "ban": 2.46
    },
    "Nidalee": {
      "win": 57.51,
      "pick": 3.26,
      "ban": 27.53
    },
    "Rengar": {
      "win": 51.83,
      "pick": 2.27,
      "ban": 2.43
    },
    "Hecarim": {
      "win": 56.88,
      "pick": 7.85,
      "ban": 84.96
    },
    "Corki": {
      "win": 50.18,
      "pick": 2.17,
      "ban": 0.02
    },
    "Gragas": {
      "win": 57.72,
      "pick": 2.36,
      "ban": 0.1
    },
    "Nilah": {
      "win": 52.77,
      "pick": 1.48,
      "ban": 0.99
    },
    "Akshan": {
      "win": 57.76,
      "pick": 1.21,
      "ban": 0.05
    }
  },
  "debug": {
    "hero_list_total": 135,
    "hero_list_version": "7.0",
    "hero_list_fileTime": "2026-02-05 11:27:37",
    "rank_rows_found": 859,
    "wr_written": 130,
    "missing_en_name_from_poster": 0,
    "filtered_not_in_wr_list": 28,
    "sample_written": [
      {
        "hero_id": "10119",
        "name": "Brand",
        "icon": "https://game.gtimg.cn/images/lgamem/act/lrlib/img/HeadIcon/H_S_10119.png",
        "stats": {
          "CN": {
            "win": 53.15,
            "pick": 10.01,
            "ban": 7.66
          }
        }
      },
      {
        "hero_id": "10138",
        "name": "Smolder",
        "icon": "https://game.gtimg.cn/images/lgamem/act/lrlib/img/HeadIcon/H_S_10138.png",
        "stats": {
          "CN": {
            "win": 56.35,
            "pick": 16.7,
            "ban": 74.47
          }
        }
      },
      {
        "hero_id": "10144",
        "name": "Viktor",
        "icon": "https://game.gtimg.cn/images/lgamem/act/lrlib/img/HeadIcon/H_S_10144.png",
        "stats": {
          "CN": {
            "win": 52.73,
            "pick": 6.4,
            "ban": 1.84
          }
        }
      },
      {
        "hero_id": "10028",
        "name": "Morgana",
        "icon": "https://game.gtimg.cn/images/lgamem/act/lrlib/img/HeadIcon/H_S_10028.png",
        "stats": {
          "CN": {
            "win": 52.7,
            "pick": 8.69,
            "ban": 32.41
          }
        }
      },
      {
        "hero_id": "10024",
        "name": "Syndra",
        "icon": "https://game.gtimg.cn/images/lgamem/act/lrlib/img/HeadIcon/H_S_10024.png",
        "stats": {
          "CN": {
            "win": 52.26,
            "pick": 9.0,
            "ban": 8.61
          }
        }
      }
    ]
  }
}